datainsightx/__init__.py
datainsightx/cli.py
datainsightx/quality.py
datainsightx/visualize.py
datainsightx_raj-0.1.1.dist-info/licenses/LICENSE
tests/__init__.py
tests/test_quality.py
tests/test_visualize.py
datainsightx_raj-0.1.1.dist-info/METADATA
datainsightx_raj-0.1.1.dist-info/WHEEL
datainsightx_raj-0.1.1.dist-info/entry_points.txt
datainsightx_raj-0.1.1.dist-info/top_level.txt
datainsightx_raj-0.1.1.dist-info/RECORD
