Metadata-Version: 2.4
Name: datainsightx-raj
Version: 0.1.1
Summary: A lightweight data quality and visualization toolkit for pandas DataFrames
Home-page: https://github.com/TRajalingam/datainsightx-raj
Author: RAJALINGAMT
Author-email: raju031001@gmail.com
Classifier: Programming Language :: Python :: 3
Classifier: License :: OSI Approved :: MIT License
Classifier: Operating System :: OS Independent
Requires-Python: >=3.8
License-File: LICENSE
Requires-Dist: pandas
Requires-Dist: numpy
Requires-Dist: plotly
Requires-Dist: jinja2
Dynamic: author
Dynamic: author-email
Dynamic: classifier
Dynamic: description
Dynamic: description-content-type
Dynamic: home-page
Dynamic: license-file
Dynamic: requires-dist
Dynamic: requires-python
Dynamic: summary
